<?xml version="1.0" encoding="UTF-8"?>
<annotation>
	<folder>Images</folder>
	<filename>IMG_kitti_0000_000063.png</filename>
	<source>
		<database>TLR</database>
	</source>
	<size>
		<width>1242</width>
		<height>375</height>
		<depth>1</depth>
	</size>
	<segmented>0</segmented>
	<object>
		<name>car</name>
		<pose>Unspecified</pose>
		<truncated>0</truncated>
		<difficult>0</difficult>
		<bndbox>
			<xmin>908.634643</xmin>
			<ymin>150.198327</ymin>
			<xmax>1067.003577</xmax>
			<ymax>241.467511</ymax>
		</bndbox>
	</object>
	<object>
		<name>person</name>
		<pose>Unspecified</pose>
		<truncated>0</truncated>
		<difficult>0</difficult>
		<bndbox>
			<xmin>801.516166</xmin>
			<ymin>155.776802</ymin>
			<xmax>896.913671</xmax>
			<ymax>340.021148</ymax>
		</bndbox>
	</object>
	<object>
		<name>car</name>
		<pose>Unspecified</pose>
		<truncated>0</truncated>
		<difficult>0</difficult>
		<bndbox>
			<xmin>1083.437634</xmin>
			<ymin>137.491023</ymin>
			<xmax>1241.000000</xmax>
			<ymax>248.256876</ymax>
		</bndbox>
	</object>
</annotation>
