<?xml version="1.0" encoding="UTF-8"?>
<annotation>
	<folder>Images</folder>
	<filename>IMG_kitti_0000_000075.png</filename>
	<source>
		<database>TLR</database>
	</source>
	<size>
		<width>1242</width>
		<height>375</height>
		<depth>1</depth>
	</size>
	<segmented>0</segmented>
	<object>
		<name>car</name>
		<pose>Unspecified</pose>
		<truncated>0</truncated>
		<difficult>0</difficult>
		<bndbox>
			<xmin>1090.710612</xmin>
			<ymin>155.238174</ymin>
			<xmax>1241.000000</xmax>
			<ymax>244.280562</ymax>
		</bndbox>
	</object>
	<object>
		<name>person</name>
		<pose>Unspecified</pose>
		<truncated>0</truncated>
		<difficult>0</difficult>
		<bndbox>
			<xmin>967.918669</xmin>
			<ymin>159.153733</ymin>
			<xmax>1060.752021</xmax>
			<ymax>330.130839</ymax>
		</bndbox>
	</object>
	<object>
		<name>car</name>
		<pose>Unspecified</pose>
		<truncated>0</truncated>
		<difficult>0</difficult>
		<bndbox>
			<xmin>1156.433190</xmin>
			<ymin>134.008875</ymin>
			<xmax>1241.000000</xmax>
			<ymax>276.932222</ymax>
		</bndbox>
	</object>
</annotation>
